causeinfer/__init__.py
causeinfer/evaluation.py
causeinfer/utils.py
causeinfer/advanced_algorithms/__init__.py
causeinfer/data/__init__.py
causeinfer/data/cmf_micro.py
causeinfer/data/download_utils.py
causeinfer/data/hillstrom.py
causeinfer/data/mayo_pbc.py
causeinfer/data/datasets/mayo_pbc.text
causeinfer/data/datasets/tamoxifen.txt
causeinfer/data/datasets/cmf_micro/2013-0533_data_baseline.dta
causeinfer/data/datasets/cmf_micro/2013-0533_data_census.dta
causeinfer/data/datasets/cmf_micro/2013-0533_data_endline1businesstype.dta
causeinfer/data/datasets/cmf_micro/2013-0533_data_endlines1and2.dta
causeinfer/data/datasets/cmf_micro/2013-0533_do_figures.do
causeinfer/data/datasets/cmf_micro/2013-0533_do_tables.do
causeinfer/data/datasets/cmf_micro/Readme.pdf
causeinfer/standard_algorithms/__init__.py
causeinfer/standard_algorithms/base_models.py
causeinfer/standard_algorithms/binary_transformation.py
causeinfer/standard_algorithms/interaction_term.py
causeinfer/standard_algorithms/pessimistic.py
causeinfer/standard_algorithms/quaternary_transformation.py
causeinfer/standard_algorithms/reflective.py
causeinfer/standard_algorithms/two_model.py
causeinfer-1.0.1.dist-info/LICENSE.txt
causeinfer-1.0.1.dist-info/METADATA
causeinfer-1.0.1.dist-info/NOTICE.txt
causeinfer-1.0.1.dist-info/WHEEL
causeinfer-1.0.1.dist-info/top_level.txt
causeinfer-1.0.1.dist-info/RECORD
