Metadata-Version: 2.1
Name: causeinfer
Version: 1.0.1
Summary: Machine learning based causal inference/uplift in Python
Home-page: https://github.com/andrewtavis/causeinfer
Author: Andrew Tavis McAllister
Author-email: andrew.t.mcallister@gmail.com
License: new BSD
Platform: UNKNOWN
Classifier: Development Status :: 5 - Production/Stable
Classifier: Intended Audience :: Developers
Classifier: Intended Audience :: Education
Classifier: Intended Audience :: Science/Research
Classifier: License :: OSI Approved :: BSD License
Classifier: Programming Language :: Python
Classifier: Programming Language :: Python :: 3
Classifier: Programming Language :: Python :: 3.6
Classifier: Programming Language :: Python :: 3.7
Classifier: Programming Language :: Python :: 3.8
Classifier: Operating System :: OS Independent
Requires-Python: >=3.6
Requires-Dist: black (>=19.10b0)
Requires-Dist: certifi (>=2020.12.5)
Requires-Dist: matplotlib (>=3.3.4)
Requires-Dist: numpy (>=1.19.2)
Requires-Dist: packaging (>=20.9)
Requires-Dist: pandas (>=1.2.3)
Requires-Dist: pytest (>=6.2.3)
Requires-Dist: pytest-cov (>=2.11.1)
Requires-Dist: requests (>=2.25.1)
Requires-Dist: scikit-learn (>=0.24.1)
Requires-Dist: seaborn (>=0.11.1)
Requires-Dist: tqdm (>=4.59.0)
